algebraIA/__init__.py
algebraIA/archivoTest.py
algebraIA/mi_modulo.py
algebraia-0.0.6.dist-info/METADATA
algebraia-0.0.6.dist-info/WHEEL
algebraia-0.0.6.dist-info/licenses/LICENSE
algebraia-0.0.6.dist-info/RECORD
