Metadata-Version: 2.1
Name: algebraIA
Version: 0.0.6
Summary: Una librería de álgebra lineal para la comunidad de IA.
Project-URL: Homepage, https://github.com/Seikened/LibreriaAlgebra
Project-URL: Bug Tracker, https://github.com/Seikened/LibreriaAlgebra/issues
Author-email: Fernando Leon Franco <leon@leonesfrancos.com>
License-File: LICENSE
Classifier: License :: OSI Approved :: MIT License
Classifier: Operating System :: OS Independent
Classifier: Programming Language :: Python :: 3
Requires-Python: >=3.7
Requires-Dist: matplotlib==3.8.1
Requires-Dist: numpy==1.26.0
Requires-Dist: scipy==1.11.3
